odoo/addons/product_attribute_archive/README.rst
odoo/addons/product_attribute_archive/__init__.py
odoo/addons/product_attribute_archive/__manifest__.py
odoo/addons/product_attribute_archive/i18n/product_attribute_archive.pot
odoo/addons/product_attribute_archive/models/__init__.py
odoo/addons/product_attribute_archive/models/product_attribute.py
odoo/addons/product_attribute_archive/models/product_attribute_value.py
odoo/addons/product_attribute_archive/readme/CONTRIBUTORS.rst
odoo/addons/product_attribute_archive/readme/DESCRIPTION.rst
odoo/addons/product_attribute_archive/readme/USAGE.rst
odoo/addons/product_attribute_archive/static/description/icon.png
odoo/addons/product_attribute_archive/static/description/index.html
odoo/addons/product_attribute_archive/views/product_attribute.xml
odoo/addons/product_attribute_archive/views/product_attribute_value.xml
odoo13_addon_product_attribute_archive-13.0.2.0.0.dist-info/METADATA
odoo13_addon_product_attribute_archive-13.0.2.0.0.dist-info/WHEEL
odoo13_addon_product_attribute_archive-13.0.2.0.0.dist-info/top_level.txt
odoo13_addon_product_attribute_archive-13.0.2.0.0.dist-info/RECORD
