Metadata-Version: 2.1
Name: odoo13-addon-product-attribute-archive
Version: 13.0.2.0.0
Summary: Add an active field on product attributes
Home-page: https://github.com/OCA/product-attribute
Author: Akretion,Odoo Community Association (OCA)
Author-email: support@odoo-community.org
License: AGPL-3
Platform: UNKNOWN
Classifier: Programming Language :: Python
Classifier: Framework :: Odoo
Classifier: Framework :: Odoo :: 13.0
Classifier: License :: OSI Approved :: GNU Affero General Public License v3
Requires-Python: >=3.5
Requires-Dist: odoo13-addon-product-attribute-value-menu
Requires-Dist: odoo (<13.1dev,>=13.0a)
